resume/__init__.py
resume/display_resume.py
akanksha-0.0.2.dist-info/METADATA
akanksha-0.0.2.dist-info/WHEEL
akanksha-0.0.2.dist-info/entry_points.txt
akanksha-0.0.2.dist-info/top_level.txt
akanksha-0.0.2.dist-info/RECORD
