Metadata-Version: 2.1
Name: akanksha
Version: 0.0.2
Summary: A deep dive into Resume of Akanksha Raj
Author: Akanksha Raj
Author-email: akanksha1601raj@gmail.com
Classifier: Programming Language :: Python :: 3
Classifier: License :: OSI Approved :: MIT License
Classifier: Operating System :: OS Independent
Requires-Python: >=3.6
